<Creature xmlns:xsd="http://www.w3.org/2001/XMLSchema" xmlns:xsi="http://www.w3.org/2001/XMLSchema-instance"><name>Barbed Devil</name><ac>15</ac><pp>18</pp><str><int>16</int><int>0</int><int>3</int></str><dex><int>17</int><int>0</int><int>3</int></dex><con><int>18</int><int>0</int><int>4</int></con><int_stat><int>12</int><int>0</int><int>1</int></int_stat><wis><int>14</int><int>0</int><int>2</int></wis><cha><int>14</int><int>0</int><int>2</int></cha><dmg><int>2</int><int>2</int><int>1</int><int>0</int><int>2</int><int>1</int><int>1</int><int>1</int><int>0</int><int>2</int><int>2</int><int>2</int><int>2</int></dmg><playable>false</playable><evasion>true</evasion><max_hp>110</max_hp><level>5</level><user_created>false</user_created></Creature>